{
  "name": "epoch-metada",
  "version": "0.1.0",
  "dependencies": [
    "armadillo",
    "atomic-queue",
    "mlpack",
    "boost-signals2",
    "catch2",
    "dataframe",
    "duckdb",
    "drogon",
    "glaze",
    "spdlog",
    "icu",
    "trompeloeil",
    "yaml-cpp",
    "protobuf",
    "tabulate",
    "tbb",
    {
      "name": "aws-sdk-cpp",
      "features": [
        "config",
        "s3",
        "transfer",
        "identity-management",
        "sts",
        "sagemaker-runtime"
      ]
    },
    {
      "name": "arrow",
      "features": [
        "acero",
        "compute",
        "csv",
        "json",
        "parquet",
        "s3",
        "filesystem"
      ]
    }
  ]
}